{
  "query": "Introduction \\label{sec:introduction} The ability of an agent to learn an informative mapping from complex observations to a succinct representation is one of the essential factors for the success of machine learning in fields such as computer vision, language modeling, and more broadly in deep learning<|cite_0|>. In supervised learning, it is",
  "paper_id": "2110.14798",
  "retrieved_ids": [
    "Bengio2013representation",
    "zhang2020dive",
    "survey3",
    "sun2019optimization",
    "geirhos2021partial",
    "khosla2020supervised",
    "relicv1",
    "trlvln",
    "hong2023learning",
    "pfeiffer2023modular",
    "chen2022weakly",
    "yang2023introduction",
    "kingma2019introduction",
    "yamada2022task",
    "tan2018survey",
    "flow1",
    "Albrecht_2018",
    "bendidi2023free",
    "menghani2021efficient",
    "Awais-arxiv-2023",
    "foerster2016learning",
    "li-etal-2023-zero",
    "chen2022semi",
    "bronstein2017geometric",
    "le2020contrastive",
    "liu2020self",
    "grover2018learning",
    "battaglia2018relational",
    "KARIMI2020101759",
    "ICLRsub2022",
    "Wang_Yu_Yu_Dai_Tsvetkov_Cao_2021",
    "hong2020language",
    "mottaghi2019adversarial",
    "Zheng2023SecretsOR",
    "Kingma2014SemisupervisedLW",
    "Wu_2016_CVPR",
    "white2023neural",
    "wang2021knowledge",
    "TRL",
    "ze2023gnfactor",
    "Ghorbani2019",
    "haochen2022theoretical",
    "wang2023images",
    "beyer2022knowledge",
    "ash2021investigating",
    "greff2020binding",
    "2016arXiv160604080V",
    "mscoco",
    "DiffsionDecisionMaking2022",
    "yoo2022groundtruth",
    "nic",
    "he2024active",
    "vinyals2017matching",
    "muller2019does",
    "perarnau2016invertible",
    "smilkov2017smoothgrad"
  ],
  "relevant_ids": [
    "Jin2020linear",
    "AgarwalKKS20",
    "Zanette2020low",
    "Modi2021modelfree",
    "hao2020adaptive",
    "DuKJAD019",
    "Bengio2013representation",
    "lu2021power",
    "papini2021leveraging"
  ],
  "metrics": {
    "R@5": 0.1111111111111111,
    "R@10": 0.1111111111111111,
    "R@20": 0.1111111111111111,
    "MRR": 1.0,
    "hits": 1,
    "total_relevant": 9
  },
  "score": 0.37777777777777777,
  "timestamp": "2025-12-18T10:57:04.977034"
}