{
  "query": "Introduction \\label{sec:intro} Generative AI has garnered significant interests in computer vision community. Recent advancements in text-driven image and video synthesis (T2I/T2V)<|cite_0|> bolstered by the advent of diffusion models<|cite_1|> exhibited remarkable ingenuity and generative quality, demonstrating considerable potential in image and video synthesis, editing, and animation. However, the synthesized images/videos are",
  "paper_id": "2307.00040",
  "retrieved_ids": [
    "zhang2023text",
    "b8",
    "yang2022diffusion",
    "ho2022video",
    "esser2023structure",
    "po2023state",
    "liao2023text",
    "ge2023preserve",
    "mao2023guided",
    "b53",
    "chen2023videocrafter1",
    "Lumiere",
    "xing2023dynamicrafter",
    "he2022synthetic",
    "wu2022tune",
    "razzhigaev2023kandinsky",
    "karras2023dreampose",
    "molad2023dreamix",
    "guo2023animatediff",
    "wang2023lavie",
    "UdiffText",
    "neuralvideofieldsediting",
    "khachatryan2023text2video",
    "customizeavideo",
    "zhang2024moonshot",
    "hu2024animate",
    "b2",
    "he2022lvdm",
    "wu2023cvpr",
    "svd",
    "b1",
    "singer2022make",
    "chen2023pixartalpha",
    "reed2016generative",
    "frolov2021adversarial",
    "yu2023quality",
    "tokenflow2023",
    "ren2024consisti2v",
    "voynov2023p+",
    "dai2023animateanything",
    "wang2023genlvideo",
    "ruta2023diffnst",
    "du2023demofusion",
    "liang2023flowvid",
    "aldausari2020video",
    "hertz2023style"
  ],
  "relevant_ids": [
    "sohl2015deep",
    "ma2023follow",
    "siarohin2019animating",
    "ge2022metadance",
    "wang2018video",
    "zhao2022thin",
    "karras2023dreampose",
    "gafni2019vid2game",
    "nichol2021glide",
    "liu2019liquid",
    "siarohin2021motion",
    "singer2022make",
    "ramesh2022hierarchical",
    "saharia2022photorealistic",
    "lee2019metapix",
    "ho2022imagen",
    "rombach2022high",
    "karras2020analyzing",
    "wu2022tune",
    "zhang2023adding",
    "jiang2023text2performer",
    "ni2023conditional",
    "song2020denoising",
    "wang2019few",
    "esser2023structure",
    "ho2022classifier",
    "song2020score",
    "siarohin2019first",
    "blattmann2021ipoke",
    "dhariwal2021diffusion",
    "chan2019everybody",
    "zhou2019dance",
    "kumari2022multi",
    "suo2022jointly",
    "xu2022versatile",
    "mahapatra2022controllable",
    "goodfellow2020generative",
    "ho2020denoising",
    "wang2022latent",
    "khachatryan2023text2video",
    "holynski2021animating",
    "brock2018large",
    "li2021ai",
    "weng2019photo"
  ],
  "metrics": {
    "R@5": 0.022727272727272728,
    "R@10": 0.022727272727272728,
    "R@20": 0.06818181818181818,
    "MRR": 0.2,
    "hits": 5,
    "total_relevant": 44
  },
  "score": 0.07590909090909091,
  "timestamp": "2025-12-18T10:53:11.711910"
}