{
  "query": "Introduction Deep convolutional neural networks are powerful and popular algorithms that achieve state-of-the-art performance in various computer vision tasks, such as object recognition. Despite the advances made by the recent architectures<|cite_0|>, they are discovered to be fragile to small but carefully directed perturbations of images<|cite_1|>, such that the targeted images",
  "paper_id": "1711.01791",
  "retrieved_ids": [
    "vgg",
    "Ghorbani2019",
    "zhao2019object",
    "geirhos2017comparing",
    "agrawal2014analyzing",
    "kang2016tcnn",
    "simonyan2013deep",
    "zhou2020universality",
    "dodge2017study",
    "nguyen2015deep",
    "zhou2014object",
    "narodytska2016simple",
    "dosovitskiy2020vit",
    "luo2016understanding",
    "elsken2019neural",
    "khan2021transformers",
    "zheng2016improving",
    "akhtar2018threat",
    "bhojanapalli2021understanding",
    "huang2017densely",
    "jung2023neural",
    "vit",
    "guo2020meets",
    "sen2020empir",
    "qusecnet",
    "deeplabv1",
    "radford2015unsupervised",
    "moosavi2016deepfool",
    "ding2023unireplknet",
    "cspnet",
    "devries2017improved",
    "gao2020patch",
    "he2014spatial",
    "he2019parametric",
    "li2021neural",
    "shao2022adversarial",
    "jakubovitz2018improving",
    "ben2019demystifying",
    "ma2021understanding",
    "xu2023resilient",
    "monti2017geometric",
    "xu2019adversarial",
    "MAXIM",
    "iandola2014densenet",
    "arnab2018robustness",
    "object_tracking_in_autunomous_driving",
    "limitations",
    "das2017keeping",
    "szegedy2017inception"
  ],
  "relevant_ids": [
    "papernot2016limitations",
    "papernot2017practical",
    "he2016deep",
    "kurakin2016adversarial",
    "moosavi2016deepfool",
    "ha2016hypernetworks",
    "papernot2016distillation",
    "metzen2017detecting",
    "szegedy2013intriguing",
    "de2016dynamic",
    "goodfellow2014explaining",
    "tabacof2016exploring",
    "narodytska2016simple",
    "simonyan2014very",
    "jin2015robust",
    "zheng2016improving",
    "szegedy2015going",
    "tramer2017ensemble"
  ],
  "metrics": {
    "R@5": 0.0,
    "R@10": 0.0,
    "R@20": 0.1111111111111111,
    "MRR": 0.08333333333333333,
    "hits": 3,
    "total_relevant": 18
  },
  "score": 0.024999999999999998,
  "timestamp": "2025-12-18T10:52:27.088525"
}